unicode_segmentation_py/__init__.py
unicode_segmentation_py/_lowlevel.abi3.so
unicode_segmentation_py/_lowlevel.pyi
unicode_segmentation_py/py.typed
unicode_segmentation_py/with_indices.py
unicode_segmentation_py-0.1.1.dist-info/METADATA
unicode_segmentation_py-0.1.1.dist-info/WHEEL
unicode_segmentation_py-0.1.1.dist-info/RECORD
unicode_segmentation_py-0.1.1.dist-info/licenses/LICENSE.txt
