Metadata-Version: 2.4
Name: unicode-segmentation-py
Version: 0.1.1
Classifier: Typing :: Typed
License-File: LICENSE.txt
Summary: Python bindings for Rust library unicode-segmentation
Keywords: unicode
Author-email: zoushun1997 <zoushun1997@163.com>
License: MIT
Requires-Python: >=3.10
Project-URL: source, https://github.com/zoushun1997/unicode-segmentation-py
